llama_index/tools/ionic_shopping/__init__.py
llama_index/tools/ionic_shopping/base.py
llama_index_tools_ionic_shopping-0.4.1.dist-info/METADATA
llama_index_tools_ionic_shopping-0.4.1.dist-info/WHEEL
llama_index_tools_ionic_shopping-0.4.1.dist-info/licenses/LICENSE
llama_index_tools_ionic_shopping-0.4.1.dist-info/RECORD
