Metadata-Version: 2.4
Name: llama-index-tools-ionic-shopping
Version: 0.4.1
Summary: llama-index tools ionic shopping integration
Author-email: Your Name <you@example.com>
Maintainer: stewartjarod
License-Expression: MIT
License-File: LICENSE
Requires-Python: <4.0,>=3.9
Requires-Dist: ionic-api-sdk<0.10,>=0.9.1
Requires-Dist: llama-index-core<0.15,>=0.13.0
